commit_crafter/__init__.py
commit_crafter/commit_crafter.py
commit_crafter_ai-1.4.5.dist-info/LICENSE
commit_crafter_ai-1.4.5.dist-info/METADATA
commit_crafter_ai-1.4.5.dist-info/WHEEL
commit_crafter_ai-1.4.5.dist-info/entry_points.txt
commit_crafter_ai-1.4.5.dist-info/top_level.txt
commit_crafter_ai-1.4.5.dist-info/RECORD
